angkajaditeks/__init__.py
angkajaditeks/angka_jadi_teks.py
angkajaditeks-1.1.dist-info/licenses/LICENSE.md
angkajaditeks-1.1.dist-info/METADATA
angkajaditeks-1.1.dist-info/WHEEL
angkajaditeks-1.1.dist-info/entry_points.txt
angkajaditeks-1.1.dist-info/top_level.txt
angkajaditeks-1.1.dist-info/RECORD
