Metadata-Version: 2.4
Name: angkajaditeks
Version: 1.1
Summary: Proyek ini menyediakan sebuah skrip Python sederhana untuk mengonversi angka (integer) menjadi ejaan yang sesuai dalam Bahasa Indonesia. Skrip ini mampu menangani angka dari nol hingga triliunan, termasuk bilangan negatif dan angka desimal.
Home-page: https://github.com/agaveingit/Teks-dari-angka.git
Author: agaveingit
Author-email: holhokgorgok@gmail.com
License: MIT
Keywords: ANGKA,MENJADI,TEKS
Classifier: Development Status :: 5 - Production/Stable
Classifier: Intended Audience :: Developers
Classifier: Topic :: Software Development :: Build Tools
Classifier: License :: OSI Approved :: MIT License
Classifier: Programming Language :: Python :: 3
Classifier: Programming Language :: Python :: 3.4
Classifier: Programming Language :: Python :: 3.5
Classifier: Programming Language :: Python :: 3.6
License-File: LICENSE.md
Dynamic: license-file
